wanna/__init__.py
wanna/chatter.py
wanna/cli.py
wanna/codedisplay.py
wanna/config.py
wanna/system.py
wanna-0.2.1.dist-info/LICENSE
wanna-0.2.1.dist-info/METADATA
wanna-0.2.1.dist-info/WHEEL
wanna-0.2.1.dist-info/entry_points.txt
wanna-0.2.1.dist-info/RECORD
